TitanOmics-0.1.data/scripts/titan.py
titanomics/__init__.py
titanomics/titan_assembly.py
titanomics/titan_decon.py
titanomics/titan_merge.py
titanomics/titan_orf.py
titanomics/titan_qc.py
titanomics/titan_trim.py
titanomics/data/PacBio_quality-control.fna
titanomics/data/adapters.fna
titanomics/data/lambda-phage.fna
titanomics/data/phix174_ill.ref.fna
titanomics/data/plotly-2.0.0.min.js
titanomics/data/style.css
TitanOmics-0.1.dist-info/LICENSE.txt
TitanOmics-0.1.dist-info/METADATA
TitanOmics-0.1.dist-info/WHEEL
TitanOmics-0.1.dist-info/top_level.txt
TitanOmics-0.1.dist-info/RECORD
