Metadata-Version: 2.1
Name: TitanOmics
Version: 0.1
Summary: A comprehensive multi-omics data analysis pipeline.
Home-page: https://github.com/raw-lab/titan
Author: Jose L. Figueroa III, Richard A. White III
Author-email: jlfiguer@uncc.edu
License: BSD License
Platform: Unix
Classifier: Development Status :: 1 - Planning
Classifier: Programming Language :: Python :: 3
Classifier: Programming Language :: Python :: 3.6
Classifier: Programming Language :: Python :: 3.7
Classifier: Programming Language :: Python :: 3.8
Classifier: Programming Language :: Python :: 3.9
Classifier: License :: OSI Approved :: BSD License
Classifier: Operating System :: Unix
Requires-Python: <3.10
License-File: LICENSE.txt
Requires-Dist: setuptools
Requires-Dist: ray
Requires-Dist: metaomestats
Requires-Dist: configargparse
Requires-Dist: psutil
Requires-Dist: grpcio (<=1.43)
